{
  "_class": "group",
  "do_objectID": "B4393BD0-6A20-4A12-8B0A-404E7EB1B11B",
  "exportOptions": {
    "_class": "exportOptions",
    "exportFormats": [
    ],
    "includedLayerIds": [
    ],
    "layerOptions": 0,
    "shouldTrim": false
  },
  "frame": {
    "_class": "rect",
    "constrainProportions": false,
    "height": 32,
    "width": 520,
    "x": 8,
    "y": 4
  },
  "hasClickThrough": false,
  "isFlippedHorizontal": false,
  "isFlippedVertical": false,
  "isLocked": false,
  "isVisible": true,
  "layerListExpandedType": 2,
  "layers": [
    {
      "class": "symbolInstance",
      "id": "F1B2565B-CEBF-4AF0-8BC5-F0910525D4E7"
    },
    {
      "class": "symbolInstance",
      "id": "B9E9DA9C-1B30-41CA-96C1-AAE25872DB77"
    },
    {
      "class": "symbolInstance",
      "id": "A1277F68-D9CE-417C-9010-94E830DE1C0C"
    },
    {
      "class": "symbolInstance",
      "id": "85E6DE55-A584-4669-9640-A815E1297736"
    },
    {
      "class": "symbolInstance",
      "id": "733F3110-8E6F-4AF8-A482-67E10C34AB68"
    },
    {
      "class": "symbolInstance",
      "id": "A076BF07-D8CB-4D47-A0E3-4C427E7E1390"
    },
    {
      "class": "symbolInstance",
      "id": "953F4FAC-56E4-484B-B7F1-1C1276524FD3"
    },
    {
      "class": "symbolInstance",
      "id": "D4EF2869-8FD9-4DA9-B46F-0EF7D861C4E2"
    }
  ],
  "name": "left-aligned",
  "nameIsFixed": true,
  "resizingConstraint": 25,
  "resizingType": 0,
  "rotation": 0,
  "shouldBreakMaskChain": false,
  "style": {
    "_class": "style",
    "endDecorationType": 0,
    "miterLimit": 10,
    "startDecorationType": 0
  }
}