{
  "_class": "shapeGroup",
  "clippingMaskMode": 0,
  "do_objectID": "11396E47-552F-48AA-9794-B407437B7850",
  "exportOptions": {
    "_class": "exportOptions",
    "exportFormats": [
    ],
    "includedLayerIds": [
    ],
    "layerOptions": 0,
    "shouldTrim": false
  },
  "frame": {
    "_class": "rect",
    "constrainProportions": false,
    "height": 24,
    "width": 456,
    "x": 0,
    "y": 4
  },
  "hasClickThrough": false,
  "hasClippingMask": false,
  "isFlippedHorizontal": false,
  "isFlippedVertical": false,
  "isLocked": false,
  "isVisible": true,
  "layerListExpandedType": 1,
  "layers": [
    {
      "class": "rectangle",
      "id": "95210FC1-B9F3-4670-ADCA-004D9B27D17E"
    }
  ],
  "name": "Rectangle 5 Copy",
  "nameIsFixed": false,
  "resizingConstraint": 63,
  "resizingType": 0,
  "rotation": 0,
  "shouldBreakMaskChain": false,
  "style": {
    "sharedObjectID": "27A7847E-69B0-49EA-B54C-4BAE6EEA4A3C"
  },
  "windingRule": 1
}