{
  "_class": "group",
  "do_objectID": "3C17BF1C-D464-4CD0-9175-D61673D71B09",
  "exportOptions": {
    "_class": "exportOptions",
    "exportFormats": [
    ],
    "includedLayerIds": [
    ],
    "layerOptions": 0,
    "shouldTrim": false
  },
  "frame": {
    "_class": "rect",
    "constrainProportions": false,
    "height": 24,
    "width": 885,
    "x": 416,
    "y": 250
  },
  "hasClickThrough": false,
  "isFlippedHorizontal": false,
  "isFlippedVertical": false,
  "isLocked": false,
  "isVisible": true,
  "layerListExpandedType": 2,
  "layers": [
    {
      "class": "shapeGroup",
      "id": "E3CF6982-9051-4FC5-9369-DEF5CE891715"
    },
    {
      "class": "group",
      "id": "11369949-3F2F-4D8C-9A48-EB3A203FC843"
    },
    {
      "class": "group",
      "id": "7C99192A-BBF8-41C8-BA30-4CD2904FEFBD"
    },
    {
      "class": "group",
      "id": "FD2139AE-AF45-4C63-B4C0-4F40842183B3"
    },
    {
      "class": "text",
      "id": "EC951490-BE17-48CB-9E9C-ABEA0DDE0487"
    }
  ],
  "name": "epic copy 3",
  "nameIsFixed": true,
  "resizingConstraint": 63,
  "resizingType": 0,
  "rotation": 0,
  "shouldBreakMaskChain": false,
  "style": {
    "_class": "style",
    "endDecorationType": 0,
    "miterLimit": 10,
    "startDecorationType": 0
  }
}