{
  "_class": "group",
  "do_objectID": "082B1958-C3B7-4A91-91E6-8E4A09802FEB",
  "exportOptions": {
    "_class": "exportOptions",
    "exportFormats": [
    ],
    "includedLayerIds": [
    ],
    "layerOptions": 0,
    "shouldTrim": false
  },
  "frame": {
    "_class": "rect",
    "constrainProportions": false,
    "height": 28,
    "width": 528,
    "x": 469,
    "y": 760
  },
  "hasClickThrough": false,
  "isFlippedHorizontal": false,
  "isFlippedVertical": false,
  "isLocked": false,
  "isVisible": true,
  "layerListExpandedType": 2,
  "layers": [
    {
      "class": "group",
      "id": "78B2734B-BD40-4084-8987-C0D8349BD9B6"
    },
    {
      "class": "text",
      "id": "4093A8FF-74A2-497E-8AC8-FEB6ABB2EBBC"
    }
  ],
  "name": "Group",
  "nameIsFixed": false,
  "resizingConstraint": 63,
  "resizingType": 0,
  "rotation": 0,
  "shouldBreakMaskChain": false,
  "style": {
    "_class": "style",
    "endDecorationType": 0,
    "miterLimit": 10,
    "shadows": [
      {
        "_class": "shadow",
        "blurRadius": 2,
        "color": {
          "_class": "color",
          "alpha": 0.5,
          "blue": 0.7294117647058823,
          "green": 0.7294117647058823,
          "red": 0.7294117647058823
        },
        "contextSettings": {
          "_class": "graphicsContextSettings",
          "blendMode": 0,
          "opacity": 1
        },
        "isEnabled": false,
        "offsetX": 0,
        "offsetY": 1,
        "spread": 0
      }
    ],
    "startDecorationType": 0
  }
}